{
    "client": "Thunder Client",
    "collectionName": "productosColeccion",
    "dateExported": "2024-03-09T02:43:21.574Z",
    "version": "1.1",
    "folders": [],
    "requests": [
        {
            "_id": "83ee64e3-d568-4a91-a3e8-36893b8b13a5",
            "colId": "818db446-c202-4b87-b11e-625ebca3b626",
            "containerId": "",
            "name": "product Post",
            "url": "http://localhost:3000/ventasApi/v1/product",
            "method": "POST",
            "sortNum": 10000,
            "created": "2024-03-07T03:14:23.223Z",
            "modified": "2024-03-09T02:34:56.877Z",
            "headers": [
                {
                    "name": "x-token",
                    "value": "eyJhbGciOiJIUzI1NiIsInR5cCI6IkpXVCJ9.eyJ1aWQiOiI2NWViY2FiNzJiZTM5ZTQxM2RkMDJmYTYiLCJpYXQiOjE3MDk5NTE2ODEsImV4cCI6MTcwOTk1NTI4MX0.CLKUogIImHElw1NhureJe0N0quPjoMURSPE5sPMw28c"
                }
            ],
            "params": [],
            "body": {
                "type": "json",
                "raw": "{\n  \"nameProduct\": \"Sopa Laky\",\n  \"description\": \"Sopa procesada, con diferentes sabores\",\n  \"price\": 5,\n  \"category\": \"Comida\",\n  \"stock\": 15\n}",
                "form": []
            },
            "reqType": "post",
            "tests": []
        },
        {
            "_id": "29a8d5ef-17ea-4480-a6cc-1341418789af",
            "colId": "818db446-c202-4b87-b11e-625ebca3b626",
            "containerId": "",
            "name": "product Get",
            "url": "http://localhost:3000/ventasApi/v1/product",
            "method": "GET",
            "sortNum": 20000,
            "created": "2024-03-07T03:14:23.224Z",
            "modified": "2024-03-07T03:14:23.224Z",
            "headers": [],
            "params": [],
            "tests": []
        },
        {
            "_id": "0c417852-e1e9-4fa9-b085-8308528cfe45",
            "colId": "818db446-c202-4b87-b11e-625ebca3b626",
            "containerId": "",
            "name": "product GetByName",
            "url": "http://localhost:3000/ventasApi/v1/product/Sopa Laky",
            "method": "GET",
            "sortNum": 30000,
            "created": "2024-03-07T03:14:23.225Z",
            "modified": "2024-03-08T14:20:54.210Z",
            "headers": [
                {
                    "name": "x-token",
                    "value": "eyJhbGciOiJIUzI1NiIsInR5cCI6IkpXVCJ9.eyJ1aWQiOiI2NWVhZmQ5OTVhNDY5Mzc4YTczODk1ZTciLCJpYXQiOjE3MDk5MDc2MTgsImV4cCI6MTcwOTkxMTIxOH0.-AwgxSOzMjZye6AEGZH9JwVV-ZANWAUtnUmu80n4OSs"
                }
            ],
            "params": [],
            "reqType": "get",
            "tests": []
        },
        {
            "_id": "e03e58ca-dbc2-4b28-9c60-ef6e7bf497c6",
            "colId": "818db446-c202-4b87-b11e-625ebca3b626",
            "containerId": "",
            "name": "product Put",
            "url": "http://localhost:3000/ventasApi/v1/product/Sopa Laky",
            "method": "PUT",
            "sortNum": 40000,
            "created": "2024-03-07T03:14:23.226Z",
            "modified": "2024-03-09T02:40:43.470Z",
            "headers": [
                {
                    "name": "x-token",
                    "value": "eyJhbGciOiJIUzI1NiIsInR5cCI6IkpXVCJ9.eyJ1aWQiOiI2NWViY2FlMmQxNmQwMTBkMDY1MjI3NDAiLCJpYXQiOjE3MDk5NTE3MjksImV4cCI6MTcwOTk1NTMyOX0.AIxnkxrpYU99avJgubKcjRHdr144tiLWUPgrG4siaC8"
                }
            ],
            "params": [],
            "body": {
                "type": "json",
                "raw": "{\n  \"nameProduct\": \"Sopa Laky\",\n  \"description\": \"Sopa procesada, con diferentes sabores\",\n  \"price\": 5,\n  \"category\": \"Comida\",\n  \"stock\": 20\n}",
                "form": []
            },
            "reqType": "put",
            "tests": []
        },
        {
            "_id": "76a9a7af-6569-45e2-a2f7-f90cabf0e707",
            "colId": "818db446-c202-4b87-b11e-625ebca3b626",
            "containerId": "",
            "name": "product Delete",
            "url": "http://localhost:3000/ventasApi/v1/product/Sopa Laky 2",
            "method": "DELETE",
            "sortNum": 50000,
            "created": "2024-03-07T03:28:56.971Z",
            "modified": "2024-03-07T03:39:26.738Z",
            "headers": [
                {
                    "name": "x-token",
                    "value": "eyJhbGciOiJIUzI1NiIsInR5cCI6IkpXVCJ9.eyJ1aWQiOiI2NWU5MzEyYWRmZDRhZDJhMzAxNjJlYWMiLCJpYXQiOjE3MDk3ODE1NTAsImV4cCI6MTcwOTc4NTE1MH0.mNwV9fVIjv_GovO3hDhn3dvNt5JCNl59CVybT3ldHmE"
                }
            ],
            "params": [],
            "tests": []
        },
        {
            "_id": "384b79c1-c91b-4c6e-a6f4-e42d05cb0981",
            "colId": "818db446-c202-4b87-b11e-625ebca3b626",
            "containerId": "",
            "name": "product Inventory",
            "url": "http://localhost:3000/ventasApi/v1/product/get/inventory",
            "method": "GET",
            "sortNum": 60000,
            "created": "2024-03-07T03:48:26.152Z",
            "modified": "2024-03-08T14:15:10.305Z",
            "headers": [
                {
                    "name": "x-token",
                    "value": "eyJhbGciOiJIUzI1NiIsInR5cCI6IkpXVCJ9.eyJ1aWQiOiI2NWVhZmQ5OTVhNDY5Mzc4YTczODk1ZTciLCJpYXQiOjE3MDk5MDcyNTYsImV4cCI6MTcwOTkxMDg1Nn0.LBMMPPIUUmNS78_gZedJVUmmr6nQK_G2pnEMjBxqlBQ"
                }
            ],
            "params": [],
            "reqType": "get",
            "tests": []
        },
        {
            "_id": "138a889d-080e-4b60-babd-66acacf29efa",
            "colId": "818db446-c202-4b87-b11e-625ebca3b626",
            "containerId": "",
            "name": "products OutOfStock",
            "url": "http://localhost:3000/ventasApi/v1/product/get/productOutOfStock",
            "method": "GET",
            "sortNum": 70000,
            "created": "2024-03-07T03:58:35.157Z",
            "modified": "2024-03-08T14:14:24.494Z",
            "headers": [
                {
                    "name": "User-Agent",
                    "value": "eyJhbGciOiJIUzI1NiIsInR5cCI6IkpXVCJ9.eyJ1aWQiOiI2NWU5MzEyYWRmZDRhZDJhMzAxNjJlYWMiLCJpYXQiOjE3MDk3ODE1NTAsImV4cCI6MTcwOTc4NTE1MH0.mNwV9fVIjv_GovO3hDhn3dvNt5JCNl59CVybT3ldHmE"
                },
                {
                    "name": "x-token",
                    "value": "eyJhbGciOiJIUzI1NiIsInR5cCI6IkpXVCJ9.eyJ1aWQiOiI2NWVhZmQ5OTVhNDY5Mzc4YTczODk1ZTciLCJpYXQiOjE3MDk5MDcyNTYsImV4cCI6MTcwOTkxMDg1Nn0.LBMMPPIUUmNS78_gZedJVUmmr6nQK_G2pnEMjBxqlBQ"
                }
            ],
            "params": [],
            "reqType": "get",
            "tests": []
        },
        {
            "_id": "cde7f77b-caf0-4fdf-9437-ad6fb9c6e1ea",
            "colId": "818db446-c202-4b87-b11e-625ebca3b626",
            "containerId": "",
            "name": "products MostSelled",
            "url": "http://localhost:3000/ventasApi/v1/product/get/productsMostSelled",
            "method": "GET",
            "sortNum": 80000,
            "created": "2024-03-07T04:09:02.160Z",
            "modified": "2024-03-08T14:14:38.095Z",
            "headers": [
                {
                    "name": "x-token",
                    "value": "eyJhbGciOiJIUzI1NiIsInR5cCI6IkpXVCJ9.eyJ1aWQiOiI2NWVhZmQ5OTVhNDY5Mzc4YTczODk1ZTciLCJpYXQiOjE3MDk5MDcyNTYsImV4cCI6MTcwOTkxMDg1Nn0.LBMMPPIUUmNS78_gZedJVUmmr6nQK_G2pnEMjBxqlBQ"
                }
            ],
            "params": [],
            "reqType": "get",
            "tests": []
        }
    ]
}